plottah/__init__.py
plottah/__main__.py
plottah/colors.py
plottah/config.py
plottah/plot_builder/__init__.py
plottah/plot_builder/builders.py
plottah/plot_builder/specific_builders.py
plottah/plot_handler/__init__.py
plottah/plot_handler/plot_handler.py
plottah/plots/__init__.py
plottah/plots/bin_event_rate_plot.py
plottah/plots/dist_plot.py
plottah/plots/plot_protocol.py
plottah/plots/roc_curve_plot.py
plottah/utils.py
plottah-1.3.1.dist-info/METADATA
plottah-1.3.1.dist-info/WHEEL
plottah-1.3.1.dist-info/RECORD
